django_migration_scripts/__init__.py
django_migration_scripts/admin.py
django_migration_scripts/apps.py
django_migration_scripts/models.py
django_migration_scripts/tests.py
django_migration_scripts/views.py
scriptsapp/__init__.py
scriptsapp/admin.py
scriptsapp/apps.py
scriptsapp/models.py
scriptsapp/tests.py
scriptsapp/views.py
django_migration_scripts-0.1.2.dist-info/LICENSE
django_migration_scripts-0.1.2.dist-info/METADATA
django_migration_scripts-0.1.2.dist-info/WHEEL
django_migration_scripts-0.1.2.dist-info/top_level.txt
django_migration_scripts-0.1.2.dist-info/RECORD
