Metadata-Version: 2.1
Name: django-migration-scripts
Version: 0.1.2
Summary: Add migration scripts seamlessly
Home-page: https://github.com/harshatba/django-migration-scripts/
Author: Harsha Tanguturi
Author-email: harshatba@gmail.com
License: MIT
Platform: UNKNOWN
Requires-Dist: Django (>=1.6)
